[
    {
      "id": "1",
      "title": "Inesa Kochur",
      "text": "“The artwork “Open” represents a traditional doorknob in theform of a hand which one can spot on the entrances of ancient buildings in Seville. The color palette of gold and black gives a touch of royalty and aristocracy. “"
    },
    {
        "id": "2",
        "title": "Miguel Valdayo Boza",
        "text": "“This work, made by the painter Elena, presents us with apainting full of meaning and with multiple readings, all of them interconnected in a general whole that tells us about the cultural heritage that we enjoy in Andalusia and wonderfully resolved in a format in which each and every one of the elements that define the work is easily identifiable.”"
      }
]